pyclock/__init__.py
pyclock_kit-0.1.1.dist-info/licenses/LICENSE
pyclock_kit-0.1.1.dist-info/METADATA
pyclock_kit-0.1.1.dist-info/WHEEL
pyclock_kit-0.1.1.dist-info/top_level.txt
pyclock_kit-0.1.1.dist-info/RECORD
