Metadata-Version: 2.4
Name: pyclock-kit
Version: 0.1.1
Summary: A simple time utility package for getting current time in various formats
Author-email: Stanislaw Kurzyp <kurzyp.st@gmail.com>
License-Expression: MIT
Project-URL: Homepage, https://github.com/yourusername/pyclock-kit
Project-URL: Documentation, https://github.com/yourusername/pyclock-kit#readme
Project-URL: Repository, https://github.com/yourusername/pyclock-kit
Project-URL: Bug Tracker, https://github.com/yourusername/pyclock-kit/issues
Keywords: time,clock,datetime,utility
Classifier: Development Status :: 3 - Alpha
Classifier: Intended Audience :: Developers
Classifier: Programming Language :: Python :: 3
Classifier: Programming Language :: Python :: 3.8
Classifier: Programming Language :: Python :: 3.9
Classifier: Programming Language :: Python :: 3.10
Classifier: Programming Language :: Python :: 3.11
Classifier: Programming Language :: Python :: 3.12
Classifier: Operating System :: OS Independent
Classifier: Topic :: Software Development :: Libraries :: Python Modules
Classifier: Topic :: Utilities
Requires-Python: >=3.8
License-File: LICENSE
Provides-Extra: dev
Requires-Dist: pytest>=7.0; extra == "dev"
Requires-Dist: pytest-cov>=4.0; extra == "dev"
Requires-Dist: black>=23.0; extra == "dev"
Requires-Dist: flake8>=6.0; extra == "dev"
Requires-Dist: mypy>=1.0; extra == "dev"
Dynamic: license-file
